{
    "indexName": "multiple-example",
    "isFile": false,
    "publications": [
        {
            "Publication URL": "https://multiple-docs.netlify.app/garage/index.html",
            "Name": "Garage Documentation"
        },
        {
            "Publication URL": "https://multiple-docs.netlify.app/mobile-phone/index.html",
            "Name": "Syncro Phone User Guide"
        },
        {
            "Publication URL": "https://multiple-docs.netlify.app/flowers/index.html",
            "Name": "Growing Flowers"
        }
    ]
}